{
    "DirectoryMonitor": {
        "name": "目录实时监控D",
        "description": "目录实时监控D",
        "labels": "云盘,工具",
        "version": "2.5.8",
        "icon": "Linkease_A.png",
        "author": "diabellstar",
        "level": 1,
        "history": {
            "v2.5.8": "fix bug",
            "v2.5.7": "修复获取目录设置配置",
            "v2.5.6": "修复软连接",
            "v2.5.5": "修复目录设置未配置媒体库目录的场景",
            "v2.5.4": "默认取目录设置，可自定义覆盖方式",
            "v2.5.3": "支持自定义开启二级分类",
            "v2.5.2": "支持联动[云盘Strm]相关插件",
            "v2.5.1": "修复媒体刮削",
            "v2.5": "兼容v2",
            "v2.4.5": "联动实时软连接插件（近媒体文件）",
            "v2.4.4": "修复刷新媒体库",
            "v2.4.3": "可选转移完刷新媒体库",
            "v2.4.2": "fix #65",
            "v2.4.1": "增加log",
            "v2.4": "修复二级目录",
            "v2.3": "去除无效变量",
            "v2.2": "优化配置一二级分类流程",
            "v2.1": "可配置是否存储转移记录",
            "v2.0": "修复不刮削不生效bug",
            "v1.8": "fix S00转移",
            "v1.7": "fix 刮削",
            "v1.6": "可配置是否刮削",
            "v1.5": "fix 消息推送",
            "v1.4": "fix 转移后路径",
            "v1.3": "修复bug",
            "v1.2": "修复订阅重复处理的bug",
            "v1.1": "自动转移链接（不刮削）",
            "v1.0": "监控云盘目录文件变化，按原文件名软连接"
        }
    },
    "TorrentTransferOrigin": {
        "name": "转移做种-QB",
        "description": "定期转移下载器中的做种任务到另一个下载器。",
        "labels": "做种",
        "version": "2.0",
        "icon": "seed.png",
        "author": "diabellstar",
        "level": 2,
        "history": {
            "v1.10.1": "优化“立即运行一次”按钮位置",
            "v1.10": "支持跳过校验（仅支持 qBittorrent）",
            "v1.9": "优化执行周期输入，需要MoviePilot v2.2.1+",
            "v1.8": "支持qbittorrent 5",
            "v1.7": "MoviePilot V2 版本自动转移做种插件",
            "v1.7.1": "修复兼容性问题"
        }
    },
    "TorrentTransferBangumi": {
        "name": "转移做种-Bangumi",
        "description": "定期转移下载器中的做种任务到另一个下载器。",
        "labels": "做种",
        "version": "2.0",
        "icon": "seed.png",
        "author": "diabellstar",
        "level": 2,
        "history": {
            "v1.10.1": "优化“立即运行一次”按钮位置",
            "v1.10": "支持跳过校验（仅支持 qBittorrent）",
            "v1.9": "优化执行周期输入，需要MoviePilot v2.2.1+",
            "v1.8": "支持qbittorrent 5",
            "v1.7": "MoviePilot V2 版本自动转移做种插件",
            "v1.7.1": "修复兼容性问题"
        }
    },
    "TorrentRemoverBt": {
        "name": "自动删种-BT",
        "description": "自动删除下载器中的下载任务。",
        "labels": "做种",
        "version": "1.0",
        "icon": "delete.jpg",
        "author": "diabellstar",
        "level": 2,
        "history": {
            "v2.2": "优化执行周期输入，需要MoviePilot v2.2.1+",
            "v2.1.1": "修复兼容MoviePilot V2 版本",
            "v2.0": "兼容MoviePilot V2 版本"
        }
    },
    "TorrentRemoverBangumi": {
        "name": "自动删种-Bangumi",
        "description": "自动删除下载器中的下载任务。",
        "labels": "做种",
        "version": "1.0",
        "icon": "delete.jpg",
        "author": "diabellstar",
        "level": 2,
        "history": {
            "v2.2": "优化执行周期输入，需要MoviePilot v2.2.1+",
            "v2.1.1": "修复兼容MoviePilot V2 版本",
            "v2.0": "兼容MoviePilot V2 版本"
        }
    },
    "TorrentPauserOrigin": {
        "name": "自动停种-QB",
        "description": "自动停止下载器中的下载任务。",
        "labels": "做种",
        "version": "2.0",
        "icon": "delete.jpg",
        "author": "diabellstar",
        "level": 2,
        "history": {
            "v2.2": "优化执行周期输入，需要MoviePilot v2.2.1+",
            "v2.1.1": "修复兼容MoviePilot V2 版本",
            "v2.0": "兼容MoviePilot V2 版本"
        }
    },
    "TorrentPauserBt": {
        "name": "自动停种-BT",
        "description": "自动停止下载器中的下载任务。",
        "labels": "做种",
        "version": "2.0",
        "icon": "delete.jpg",
        "author": "diabellstar",
        "level": 2,
        "history": {
            "v2.2": "优化执行周期输入，需要MoviePilot v2.2.1+",
            "v2.1.1": "修复兼容MoviePilot V2 版本",
            "v2.0": "兼容MoviePilot V2 版本"
        }
    },
    "TorrentPauserBangumi": {
        "name": "自动停种-Bangumi",
        "description": "自动停止下载器中的下载任务。",
        "labels": "做种",
        "version": "2.0",
        "icon": "delete.jpg",
        "author": "diabellstar",
        "level": 2,
        "history": {
            "v2.2": "优化执行周期输入，需要MoviePilot v2.2.1+",
            "v2.1.1": "修复兼容MoviePilot V2 版本",
            "v2.0": "兼容MoviePilot V2 版本"
        }
    }

}
